fastapi_fsp/__init__.py
fastapi_fsp/fsp.py
fastapi_fsp/models.py
fastapi_fsp-0.2.1.dist-info/METADATA
fastapi_fsp-0.2.1.dist-info/WHEEL
fastapi_fsp-0.2.1.dist-info/licenses/LICENSE
fastapi_fsp-0.2.1.dist-info/RECORD
