Metadata-Version: 2.4
Name: fastapi-fsp
Version: 0.2.1
Summary: Filter, Sort, and Paginate (FSP) utilities for FastAPI + SQLModel
Project-URL: Homepage, https://github.com/fromej-dev/fastapi-fsp
Project-URL: Repository, https://github.com/fromej-dev/fastapi-fsp
Project-URL: Issues, https://github.com/fromej-dev/fastapi-fsp/issues
Author-email: Evert Jan Stamhuis <ej@fromejdevelopment.nl>
License: MIT
License-File: LICENSE
Keywords: api,fastapi,filtering,pagination,sorting,sqlmodel
Classifier: Development Status :: 3 - Alpha
Classifier: Framework :: FastAPI
Classifier: Intended Audience :: Developers
Classifier: License :: OSI Approved :: MIT License
Classifier: Programming Language :: Python
Classifier: Programming Language :: Python :: 3
Classifier: Programming Language :: Python :: 3.12
Classifier: Programming Language :: Python :: 3.13
Classifier: Programming Language :: Python :: 3.14
Classifier: Topic :: Internet :: WWW/HTTP
Classifier: Topic :: Software Development :: Libraries :: Python Modules
Requires-Python: >=3.12
Requires-Dist: fastapi>=0.121.1
Requires-Dist: python-dateutil>=2.9.0.post0
Requires-Dist: sqlmodel>=0.0.27
